ridesims/__init__.py
ridesims/__main__.py
ridesims/cli_app.py
ridesims/rides/Everest/__init__.py
ridesims/rides/Everest/everest-keyboard-commands.png
ridesims/rides/Everest/main.py
ridesims/rides/Everest/README.md
ridesims/rides/SplashMountain/__init__.py
ridesims/rides/SplashMountain/main.py
ridesims/rides/SplashMountain/README.md
ridesims/utils.py
ridesims-0.1.0.dist-info/entry_points.txt
ridesims-0.1.0.dist-info/WHEEL
ridesims-0.1.0.dist-info/METADATA
ridesims-0.1.0.dist-info/RECORD
